rerp_module/__init__.py
rerp_module/classes.py
rerp_module-0.0.3.dist-info/METADATA
rerp_module-0.0.3.dist-info/WHEEL
rerp_module-0.0.3.dist-info/top_level.txt
rerp_module-0.0.3.dist-info/RECORD
